process_flow_modules/OpenAIModule.py
process_flow_modules/OutlookModule.py
process_flow_modules/__init__.py
LundProcessFlowModules-1.0.6.dist-info/LICENSE.txt
LundProcessFlowModules-1.0.6.dist-info/METADATA
LundProcessFlowModules-1.0.6.dist-info/WHEEL
LundProcessFlowModules-1.0.6.dist-info/top_level.txt
LundProcessFlowModules-1.0.6.dist-info/RECORD
