Metadata-Version: 2.1
Name: LundProcessFlowModules
Version: 1.0.6
Summary: A Python library to use 3rd party APIs in your project directly
Home-page: https://github.com/LundIT/ProcessFlowModules
Author: Melih Sünbül
Author-email: m.sunbul@lund-it.com
License: UNKNOWN
Platform: UNKNOWN
Classifier: Programming Language :: Python :: 3
Classifier: License :: OSI Approved :: MIT License
Classifier: Operating System :: OS Independent
Requires-Python: >=3.6
Requires-Dist: openai (==0.28)
Requires-Dist: msal
